[
    {
        "kata_besemah": "ighiq, ngighiq",
        "kata_indonesia": "irik, melepaskan padi dari tangkainya",
        "kata_inggris": "detach paddy from its stalk",
        "kalimat_besemah": "Mbaq ini jeme lapang ngighiq, ghapatlah dibaduqka saje",
        "kalimat_indonesia": "Sekarang orang jarang mengirik padi, tapi dipulkan saja",
        "kalimat_inggris": "Now, paddy is not detached anymore, but simply tapped"
    },
    {
        "kata_besemah": "ighis",
        "kata_indonesia": "iris",
        "kata_inggris": "slice",
        "kalimat_besemah": "",
        "kalimat_indonesia": "",
        "kalimat_inggris": ""
    },
    {
        "kata_besemah": "ngighis",
        "kata_indonesia": "potong tipis-tipis",
        "kata_inggris": "slice very thin",
        "kalimat_besemah": "ngighis radang kandiq keripik",
        "kalimat_indonesia": "Mengiris kentang untuk kripik",
        "kalimat_inggris": "Slicing potato for crispy chips"
    },
    {
        "kata_besemah": "diighis",
        "kata_indonesia": "diiris",
        "kata_inggris": "sliced",
        "kalimat_besemah": "",
        "kalimat_indonesia": "",
        "kalimat_inggris": ""
    },
    {
        "kata_besemah": "ighisan",
        "kata_indonesia": "irisan, potongan tipis-tipis",
        "kata_inggris": "slices",
        "kalimat_besemah": "",
        "kalimat_indonesia": "",
        "kalimat_inggris": ""
    },
    {
        "kata_besemah": "ighup, ngighup",
        "kata_indonesia": "hirup, menghirup",
        "kata_inggris": "sniff",
        "kalimat_besemah": "Deghup-deghup ngighupi kuwah pindang",
        "kalimat_indonesia": "Terdengar suara deghup-deghup orang menghirup kuwah pindang",
        "kalimat_inggris": "Sniffing sauce preserved fish causes the sound deghup-deghup"
    },
    {
        "kata_besemah": "iguq",
        "kata_indonesia": "goyangan kepala saat berjalan",
        "kata_inggris": "shaking the head while walking",
        "kalimat_besemah": "",
        "kalimat_indonesia": "",
        "kalimat_inggris": ""
    },
    {
        "kata_besemah": "ngiguq-ngiguq (ngengiguq)",
        "kata_indonesia": "menggoyangkan kepala",
        "kata_inggris": "shaking the head",
        "kalimat_besemah": "Sampai di kebun tekinaqlah li kancil ade jeme ngiguq-ngiguq tengah kebun",
        "kalimat_indonesia": "Sesampai di kebun terlihat oleh si kancil ada orang yang bergoyang-goyang di tengah kebun",
        "kalimat_inggris": "Arriving at the garden, the rabbit saw there was a man shaking his head in the garden"
    },
    {
        "kata_besemah": "ih",
        "kata_indonesia": "oh, ayo...; kata seru yang digunakan apabila merasa kesal atau marah",
        "kata_inggris": "oh come on; interjection used to express the annoyance or angriness",
        "kalimat_besemah": "ih, melawan dengan ini",
        "kalimat_indonesia": "Ayo, kalau berani",
        "kalimat_inggris": "Come on if you are manfull"
    },
    {
        "kata_besemah": "ijang",
        "kata_indonesia": "hijau",
        "kata_inggris": "green",
        "kalimat_besemah": "",
        "kalimat_indonesia": "",
        "kalimat_inggris": ""
    },
    {
        "kata_besemah": "keijangan",
        "kata_indonesia": "terlalu hijau",
        "kata_inggris": "greenery",
        "kalimat_besemah": "",
        "kalimat_indonesia": "",
        "kalimat_inggris": ""
    },
    {
        "kata_besemah": "keijang-ijangan",
        "kata_indonesia": "agak hijau",
        "kata_inggris": "greenish",
        "kalimat_besemah": "",
        "kalimat_indonesia": "",
        "kalimat_inggris": ""
    },
    {
        "kata_besemah": "ijaq",
        "kata_indonesia": "injak",
        "kata_inggris": "step",
        "kalimat_besemah": "",
        "kalimat_indonesia": "",
        "kalimat_inggris": ""
    },
    {
        "kata_besemah": "ngijaqka",
        "kata_indonesia": "menginjak",
        "kata_inggris": "step on",
        "kalimat_besemah": "Ui... Jangan ngijaqka ketingku",
        "kalimat_indonesia": "Oh... Jangan menginjak kaki saya",
        "kalimat_inggris": "Wow... Don't step on my foot"
    },
    {
        "kata_besemah": "ngijaqka palaq",
        "kata_indonesia": "menghina",
        "kata_inggris": "humiliate",
        "kalimat_besemah": "",
        "kalimat_indonesia": "",
        "kalimat_inggris": ""
    },
    {
        "kata_besemah": "teghijaq",
        "kata_indonesia": "terinjak",
        "kata_inggris": "stepped",
        "kalimat_besemah": "Banyaq jemaah aji matiq teghijaq-teghijaq di teruwungan Mina",
        "kalimat_indonesia": "Banyak jemaah haji meninggal terinjak-terinjak di terowongan Mina",
        "kalimat_inggris": "Many Hajjs died because of being stepped in Mina Tunnel"
    },
    {
        "kata_besemah": "ijat",
        "kata_indonesia": "biji",
        "kata_inggris": "seed",
        "kalimat_besemah": "ijat nangka",
        "kalimat_indonesia": "biji nangka",
        "kalimat_inggris": "jackfruit seed"
    },
    {
        "kata_besemah": "beijat",
        "kata_indonesia": "berbiji, mempunyai biji",
        "kata_inggris": "seedy",
        "kalimat_besemah": "Semangke ini diq beijat",
        "kalimat_indonesia": "Semangka ini tidak ada bijinya",
        "kalimat_inggris": "This water melon is seedless"
    },
    {
        "kata_besemah": "ijatan",
        "kata_indonesia": "terdapat banyak biji",
        "kata_inggris": "having many seeds",
        "kalimat_besemah": "",
        "kalimat_indonesia": "",
        "kalimat_inggris": ""
    },
    {
        "kata_besemah": "sijat, seijat",
        "kata_indonesia": "satu biji",
        "kata_inggris": "numeral coefficient for fruits",
        "kalimat_besemah": "Pacaq mbeli duku sijat?",
        "kalimat_indonesia": "Bisa beli duku satu biji?",
        "kalimat_inggris": "Can I buy one lanseh?"
    },
    {
        "kata_besemah": "sesijat",
        "kata_indonesia": "sebiji-sebiji",
        "kata_inggris": "one by one",
        "kalimat_besemah": "",
        "kalimat_indonesia": "",
        "kalimat_inggris": ""
    },
    {
        "kata_besemah": "sesijatan",
        "kata_indonesia": "biji-biji tertentu saja",
        "kata_inggris": "certain things only",
        "kalimat_besemah": "",
        "kalimat_indonesia": "",
        "kalimat_inggris": ""
    },
    {
        "kata_besemah": "ije",
        "kata_indonesia": "usaha",
        "kata_inggris": "effort",
        "kalimat_besemah": "",
        "kalimat_indonesia": "",
        "kalimat_inggris": ""
    },
    {
        "kata_besemah": "beghije",
        "kata_indonesia": "berusaha",
        "kata_inggris": "endeavor",
        "kalimat_besemah": "Palah kite beghije!",
        "kalimat_indonesia": "Mari kita berusaha!",
        "kalimat_inggris": "Let’s try"
    },
    {
        "kata_besemah": "ngije",
        "kata_indonesia": "mengusahakan",
        "kata_inggris": "carry on",
        "kalimat_besemah": "",
        "kalimat_indonesia": "",
        "kalimat_inggris": ""
    },
    {
        "kata_besemah": "ngije",
        "kata_indonesia": "istilah untuk menggambarkan orang ketika membaca Al Qur'an masih sangat terbata-bata",
        "kata_inggris": "term used to describe s.o reading Qur'an influenly",
        "kalimat_besemah": "",
        "kalimat_indonesia": "",
        "kalimat_inggris": ""
    },
    {
        "kata_besemah": "ngijeka",
        "kata_indonesia": "mengusahakan",
        "kata_inggris": "effort",
        "kalimat_besemah": "Luq manelah kami ka ngijekanye?",
        "kalimat_indonesia": "Bagaimanakah kami bisa mengusahakannya?",
        "kalimat_inggris": "How can I carry on it"
    }
]