[
  {
    "kata_besemah": "pancue",
    "kata_indonesia": "pancuran",
    "kata_inggris": "jet of water, shower, tap, faucet",
    "kalimat_besemah": "Kami di dusun mandi nga nyabun di ayig pancue",
    "kalimat_indonesia": "Kami di kampung mandi dan cuci pada air pancuran",
    "kalimat_inggris": "In the village, we take a bath and do laudry thing by using water from a shower"
  },
  {
    "kata_besemah": "pancung",
    "kata_indonesia": "pancung, tebas",
    "kata_inggris": "cut, clear away",
    "kalimat_besemah": "",
    "kalimat_indonesia": "",
    "kalimat_inggris": ""
  },
  {
    "kata_besemah": "mancung",
    "kata_indonesia": "memancung",
    "kata_inggris": "to cut, clear away",
    "kalimat_besemah": "Mancung sawi pati",
    "kalimat_indonesia": "Memancung sawi pahit",
    "kalimat_inggris": "To harvest bitter spinach mustard"
  },
  {
    "kata_besemah": "pancungan",
    "kata_indonesia": "hasil memancung",
    "kata_inggris": "harvest",
    "kalimat_besemah": "",
    "kalimat_indonesia": "",
    "kalimat_inggris": ""
  },
  {
    "kata_besemah": "pandak",
    "kata_indonesia": "henti",
    "kata_inggris": "stop",
    "kalimat_besemah": "",
    "kalimat_indonesia": "",
    "kalimat_inggris": ""
  },
  {
    "kata_besemah": "mandak",
    "kata_indonesia": "berhenti",
    "kata_inggris": "stopped",
    "kalimat_besemah": "Ngape kite mandak di sini?",
    "kalimat_indonesia": "Mengapa kita berhenti di sini?",
    "kalimat_inggris": "Why are we stopping here?"
  },
  {
    "kata_besemah": "pandakka",
    "kata_indonesia": "hentikan",
    "kata_inggris": "stop",
    "kalimat_besemah": "Pandakka dikti mubil itu!",
    "kalimat_indonesia": "Tolong hentikan angkot itu!",
    "kalimat_inggris": "Stop that public transportation, please!"
  },
  {
    "kata_besemah": "pemandakan",
    "kata_indonesia": "tempat berhenti",
    "kata_inggris": "halte, bus shelter",
    "kalimat_besemah": "",
    "kalimat_indonesia": "",
    "kalimat_inggris": ""
  },
  {
    "kata_besemah": "pandan",
    "kata_indonesia": "pandan, suatu jenis tumbuhan berdaun panjang yang dipakai sebagai pengharum makanan",
    "kata_inggris": "pandanus, a plant with long sweet-smelling leaves whose thorns are used for weaving food",
    "kalimat_besemah": "Kalu mbuat davat agi, enjuqi pandan nga nangke mangke ghum",
    "kalimat_indonesia": "Apabila membuat cendol lagi, beri pandan dan nangka supaya wangi",
    "kalimat_inggris": "If you make cendol again, put some pandanus leaves and jackfruit to give nice smell"
  },
  {
    "kata_besemah": "pandaq",
    "kata_indonesia": "pendek",
    "kata_inggris": "short",
    "kalimat_besemah": "Jemenye pandaq, bungua, itam, anye npua luq itu attnye katah iluge",
    "kalimat_indonesia": "Orangnya pendek gemuk, hitam, walaupun demikian hatinya sangat baik",
    "kalimat_inggris": "Although he is short, overweight, and dark skinned, he is a kind-hearted man"
  },
  {
    "kata_besemah": "kepandagan",
    "kata_indonesia": "kependekan",
    "kata_inggris": "too short",
    "kalimat_besemah": "",
    "kalimat_indonesia": "",
    "kalimat_inggris": ""
  },
  {
    "kata_besemah": "pandas",
    "kata_indonesia": "istilah yang digunakan untuk pembicaraan antara keluarga calon suami dan istri untuk mencari kesepaktatan tentang pelaksanaan hari perkawinan",
    "kata_inggris": "term for negotiation between a fiance and fiancee's family to seek agreement on the implementation of the marriage",
    "kalimat_besemah": "",
    "kalimat_indonesia": "",
    "kalimat_inggris": ""
  },
  {
    "kata_besemah": "bepandas",
    "kata_indonesia": "istilah yang digunakan untuk pembicaraan antara keluarga calon suami dan istri untuk mencari kesepaktatan tentang pelaksanaan hari perkawinan",
    "kata_inggris": "term for negotiation between a fiance and fiancee's family to seek agreement on the implementation of the marriage",
    "kalimat_besemah": "Aku ndaq ngajaq manaq bepandas malam isua",
    "kalimat_indonesia": "Saya ingin mengajak paman untuk membicarakan hari pernikahan besok malam",
    "kalimat_inggris": "I would like to invite uncle to talk about the wedding day tomorrow night"
  },
  {
    "kata_besemah": "Pandigh",
    "kata_indonesia": "tokoh dalam cerita dongeng tentang sso yang bodoh bernama Pandigh",
    "kata_inggris": "a character in a folktale about a dummy man named Pandigh",
    "kalimat_besemah": "Pandigh tingaq, Pandigh bange",
    "kalimat_indonesia": "Pandir tolol Pandir bodoh",
    "kalimat_inggris": "Pandir's silly, Pandir's stupid"
  },
  {
    "kata_besemah": "pandu",
    "kata_indonesia": "sambung",
    "kata_inggris": "continue, go on",
    "kalimat_besemah": "",
    "kalimat_indonesia": "",
    "kalimat_inggris": ""
  },
  {
    "kata_besemah": "andu-bepandu",
    "kata_indonesia": "sambung menyambung",
    "kata_inggris": "continuing, on going",
    "kalimat_besemah": "Mani lahai andu-bepandu",
    "kalimat_indonesia": "Suara tertawa sambung-menyambung",
    "kalimat_inggris": "There is laughter heard after the other laughter"
  }
]