[
    {
        "kata_besemah": "caluq",
        "kata_indonesia": "terasi",
        "kata_inggris": "condiment of fermented shrimp",
        "kalimat_besemah": "sambal terasi; Mentuq terasi yang berasal dari Mentok, Pulau Bangka",
        "kalimat_indonesia": "sambal terasi; Terasi yang berasal dari Mentok, Pulau Bangka",
        "kalimat_inggris": "terasi condiment; terasi made in Mentok, Bangka Island"
    },
    {
        "kata_besemah": "embau caluq",
        "kata_indonesia": "bau terasi",
        "kata_inggris": "unpleasant smell",
        "kalimat_besemah": "",
        "kalimat_indonesia": "",
        "kalimat_inggris": ""
    },
    {
        "kata_besemah": "embau caluq",
        "kata_indonesia": "ungkapan yang dikatakan untuk orang yang badannya bau",
        "kata_inggris": "a term for people who have bad smell",
        "kalimat_besemah": "",
        "kalimat_indonesia": "",
        "kalimat_inggris": ""
    },
    {
        "kata_besemah": "camai",
        "kata_indonesia": "bertengkar",
        "kata_inggris": "clash, quarrel",
        "kalimat_besemah": "Ngape kamu ni camai saje?",
        "kalimat_indonesia": "Kenapa kalian ini selalu bertengkar?",
        "kalimat_inggris": "Why do you always quarrel?"
    },
    {
        "kata_besemah": "cambah",
        "kata_indonesia": "kecambah",
        "kata_inggris": "sprout",
        "kalimat_besemah": "kacang ijang nga cambah kacang kuning",
        "kalimat_indonesia": "Kecambah dari kacang hijau dan kecambah dari kacang kuning",
        "kalimat_inggris": "Sprout of green and yellow bean"
    },
    {
        "kata_besemah": "campuh",
        "kata_indonesia": "mulai",
        "kata_inggris": "begin, start",
        "kalimat_besemah": "Mpai campuh benagh ngetam, aghi ujan angin",
        "kalimat_indonesia": "Baru mulai mengetam, hari hujan deras",
        "kalimat_inggris": "Just beginning to harvest, it rained heavily"
    },
    {
        "kata_besemah": "cancang",
        "kata_indonesia": "berdiri tegak",
        "kata_inggris": "stand upright",
        "kalimat_besemah": "cancang-ka!",
        "kalimat_indonesia": "Tonggakkan!",
        "kalimat_inggris": "Make it upright!"
    },
    {
        "kata_besemah": "tecancang",
        "kata_indonesia": "berdiri dalam waktu yang lama di suatu tempat",
        "kata_inggris": "standing for long time in yard",
        "kalimat_besemah": "",
        "kalimat_indonesia": "",
        "kalimat_inggris": ""
    },
    {
        "kata_besemah": "becancangan",
        "kata_indonesia": "pada berdiri semua",
        "kata_inggris": "all people are standing",
        "kalimat_besemah": "",
        "kalimat_indonesia": "",
        "kalimat_inggris": ""
    },
    {
        "kata_besemah": "cancung",
        "kata_indonesia": "marah",
        "kata_inggris": "angry",
        "kalimat_besemah": "",
        "kalimat_indonesia": "",
        "kalimat_inggris": ""
    },
    {
        "kata_besemah": "ncancungi",
        "kata_indonesia": "memarahi",
        "kata_inggris": "angry with",
        "kalimat_besemah": "Kabah baih ngiciqinye, aku lah nyagu ncancungi nye",
        "kalimat_indonesia": "Engkau saja menasehatinya, saya sudah bosan memarahinya",
        "kalimat_inggris": "You have to advise him, I am bored to be angry with him"
    },
    {
        "kata_besemah": "candu",
        "kata_indonesia": "candu, sebangsa narkoba yang membuat orang bisa ketagihan bila mengkonsumsinya",
        "kata_inggris": "It is such an addictive drug",
        "kalimat_besemah": "",
        "kalimat_indonesia": "",
        "kalimat_inggris": ""
    },
    {
        "kata_besemah": "kecanduwan",
        "kata_indonesia": "ketagihan; ungkapan untuk mengatakan orang yang ingin terus melakukan ssu bila telah mencobanya",
        "kata_inggris": "addictive; addictive/addicted people",
        "kalimat_besemah": "",
        "kalimat_indonesia": "",
        "kalimat_inggris": ""
    },
    {
        "kata_besemah": "cangaq, ncangaq",
        "kata_indonesia": "buka, membuka",
        "kata_inggris": "open, to open",
        "kalimat_besemah": "",
        "kalimat_indonesia": "",
        "kalimat_inggris": ""
    },
    {
        "kata_besemah": "ncangaq-ncangaq (ncencangaq)",
        "kata_indonesia": "marah-marah dengan suara keras",
        "kata_inggris": "grumble angrily and loudly",
        "kalimat_besemah": "",
        "kalimat_indonesia": "",
        "kalimat_inggris": ""
    },
    {
        "kata_besemah": "tecangaq",
        "kata_indonesia": "terbuka",
        "kata_inggris": "opened",
        "kalimat_besemah": "Ngape duahe tengkiyang kamu tecangaq?",
        "kalimat_indonesia": "Kenapa pintu gudangmu terbuka?",
        "kalimat_inggris": "Why is your rice-warehouse opened?"
    },
    {
        "kata_besemah": "dicangaqi",
        "kata_indonesia": "dimarahi",
        "kata_inggris": "scolded",
        "kalimat_besemah": "Lemaq gi adaq kabah dicangaq-cangaqinye",
        "kalimat_indonesia": "Kasian engkau dimarah-marahinya",
        "kalimat_inggris": "It is pity that you were scolded by him"
    },
    {
        "kata_besemah": "canggih",
        "kata_indonesia": "licik, suka minta tidak suka memberi",
        "kata_inggris": "sly, tricky, crafty, wily, suka minta tidak suka memberi",
        "kalimat_besemah": "Ai kerbai tu canggih benagh, kebile beghusiq ke ghumah jeme mpuq dikit ndaq ghulih sesuatu sekalipun sedikit",
        "kalimat_indonesia": "Wah ibu itu licik sekali, setiap berkunjung ke rumah orang, ingin dapat sesuatu sekalipun sedikit",
        "kalimat_inggris": "The woman is very sly, she wants to have something any time in her visits"
    }
]